{
  "$schema": "https://dl.viam.dev/module.schema.json",
  "module_id": "ethanlook:randomrover",
  "visibility": "private",
  "url": "https://github.com/ethanlookpotts/viam-rover-random-module",
  "description": "Modular generic service: randomrover",
  "models": [
    {
      "api": "rdk:service:generic",
      "model": "ethanlook:randomrover:randomrover"
    }
  ],
  "entrypoint": "dist/main",
  "first_run": "",
  "build": {
    "build": "./build.sh",
    "setup": "./setup.sh",
    "path": "dist/archive.tar.gz",
    "arch": [
      "linux/amd64",
      "linux/arm64"
    ]
  }
}
